_super_rpa/__init__.py
_super_rpa/super_pypackage/__init__.py
_super_rpa/super_pypackage/file_text/__init__.py
_super_rpa/super_pypackage/file_text/py_csv.py
_super_rpa/super_pypackage/file_text/py_excel.py
_super_rpa/super_pypackage/file_text/py_files.py
_super_rpa/super_pypackage/file_text/py_ini.py
_super_rpa/super_pypackage/file_text/py_txt.py
_super_rpa/super_pypackage/py_automation/__init__.py
_super_rpa/super_pypackage/py_automation/keyboard.py
_super_rpa/super_pypackage/py_selenium/__init__.py
_super_rpa/super_pypackage/py_selenium/py_selenium.py
_super_rpa/super_pypackage/py_selenium/py_selenium_js.py
super_rpa/__init__.py
super_rpa/super_pypackage/__init__.py
super_rpa/super_pypackage/file_text/__init__.py
super_rpa/super_pypackage/file_text/py_csv.py
super_rpa/super_pypackage/file_text/py_excel.py
super_rpa/super_pypackage/file_text/py_files.py
super_rpa/super_pypackage/file_text/py_ini.py
super_rpa/super_pypackage/file_text/py_txt.py
super_rpa/super_pypackage/py_automation/__init__.py
super_rpa/super_pypackage/py_automation/keyboard.py
super_rpa/super_pypackage/py_selenium/__init__.py
super_rpa/super_pypackage/py_selenium/py_selenium.py
super_rpa/super_pypackage/py_selenium/py_selenium_js.py
super_rpa-0.1.4.dist-info/LICENSE.txt
super_rpa-0.1.4.dist-info/METADATA
super_rpa-0.1.4.dist-info/WHEEL
super_rpa-0.1.4.dist-info/top_level.txt
super_rpa-0.1.4.dist-info/RECORD
